MANIFEST.in
VERSION
setup.py
aegisx.ext.rfc3161.egg-info/PKG-INFO
aegisx.ext.rfc3161.egg-info/SOURCES.txt
aegisx.ext.rfc3161.egg-info/dependency_links.txt
aegisx.ext.rfc3161.egg-info/requires.txt
aegisx.ext.rfc3161.egg-info/top_level.txt
aegisx/ext/rfc3161/__init__.py
aegisx/ext/rfc3161/_client.py
aegisx/ext/rfc3161/const.py
aegisx/ext/rfc3161/package.json
aegisx/ext/rfc3161/utils.py
aegisx/ext/rfc3161/models/__init__.py
aegisx/ext/rfc3161/models/_issuer.py
aegisx/ext/rfc3161/models/_signature.py
aegisx/ext/rfc3161/models/_timestamptoken.py
aegisx/ext/rfc3161/protocols/__init__.py
aegisx/ext/rfc3161/protocols/_itimestampclient.py
aegisx/ext/rfc3161/types/__init__.py
aegisx/ext/rfc3161/types/_accuracy.py
aegisx/ext/rfc3161/types/_anothername.py
aegisx/ext/rfc3161/types/_generalname.py
aegisx/ext/rfc3161/types/_messageimprint.py
aegisx/ext/rfc3161/types/_pkifailureinfo.py
aegisx/ext/rfc3161/types/_pkifreetext.py
aegisx/ext/rfc3161/types/_pkistatus.py
aegisx/ext/rfc3161/types/_pkistatusinfo.py
aegisx/ext/rfc3161/types/_timestampauthority.py
aegisx/ext/rfc3161/types/_timestampinfo.py
aegisx/ext/rfc3161/types/_timestamprequest.py
aegisx/ext/rfc3161/types/_timestampresponse.py
aegisx/ext/rfc3161/types/_timestamptoken.py
aegisx/ext/rfc3161/types/_tsapolicyid.py